design.sv
module ring_counter (
    input clk,
    input reset,
    output reg [3:0] out
);

always @(posedge clk or posedge reset) begin
    if (reset)
        out <= 4'b1000; 
    else
        out <= {out[2:0], out[3]};
end

endmodule

testbench.sv
module tb_ring_counter;
    reg clk, reset;
    wire [3:0] out;

    ring_counter uut (
        .clk(clk),
        .reset(reset),
        .out(out)
    );

    initial begin
        clk = 0;
        forever #5 clk = ~clk;
    end

    initial begin
        reset = 1;
        #10 reset = 0;
        #100 $finish;
    end

    initial begin
      $dumpfile("ring_counter.vcd");
      $dumpvars;
        $monitor("Time = %0d : out = %b", $time, out);
    end
endmodule

ring_counter.vcd
$date
	Tue Jul 29 09:57:22 2025
$end
$version
	Icarus Verilog
$end
$timescale
	1s
$end
$scope module tb_ring_counter $end
$var wire 4 ! out [3:0] $end
$var reg 1 " clk $end
$var reg 1 # reset $end
$scope module uut $end
$var wire 1 " clk $end
$var wire 1 # reset $end
$var reg 4 $ out [3:0] $end
$upscope $end
$upscope $end
$enddefinitions $end
$comment Show the parameter values. $end
$dumpall
$end
#0
$dumpvars
b1000 $
1#
0"
b1000 !
$end
#5
1"
#10
0"
0#
#15
b1 !
b1 $
1"
#20
0"
#25
b10 !
b10 $
1"
#30
0"
#35
b100 !
b100 $
1"
#40
0"
#45
b1000 !
b1000 $
1"
#50
0"
#55
b1 !
b1 $
1"
#60
0"
#65
b10 !
b10 $
1"
#70
0"
#75
b100 !
b100 $
1"
#80
0"
#85
b1000 !
b1000 $
1"
#90
0"
#95
b1 !
b1 $
1"
#100
0"
#105
b10 !
b10 $
1"
